MANIFEST.in
README.rst
setup.py
docs/HISTORY.txt
docs/INSTALL.txt
docs/LICENSE.GPL
docs/LICENSE.txt
ftw/__init__.py
ftw.news.egg-info/PKG-INFO
ftw.news.egg-info/SOURCES.txt
ftw.news.egg-info/dependency_links.txt
ftw.news.egg-info/entry_points.txt
ftw.news.egg-info/namespace_packages.txt
ftw.news.egg-info/not-zip-safe
ftw.news.egg-info/requires.txt
ftw.news.egg-info/top_level.txt
ftw/news/__init__.py
ftw/news/configure.zcml
ftw/news/indexer.py
ftw/news/interfaces.py
ftw/news/lawgiver.zcml
ftw/news/permissions.zcml
ftw/news/resources.zcml
ftw/news/testing.py
ftw/news/utils.py
ftw/news/vocabularies.py
ftw/news/behaviors/__init__.py
ftw/news/behaviors/configure.zcml
ftw/news/behaviors/external_url.py
ftw/news/behaviors/mopage.py
ftw/news/behaviors/show_on_homepage/__init__.py
ftw/news/behaviors/show_on_homepage/news.py
ftw/news/behaviors/show_on_homepage/news_listing_block.py
ftw/news/browser/__init__.py
ftw/news/browser/configure.zcml
ftw/news/browser/mopage.py
ftw/news/browser/news_listing.py
ftw/news/browser/news_listing_block.py
ftw/news/browser/resources/archive.js
ftw/news/browser/resources/archive.scss
ftw/news/browser/resources/main.css
ftw/news/browser/resources/main.js
ftw/news/browser/resources/news-compiled.css
ftw/news/browser/resources/news-compiled.js
ftw/news/browser/resources/news.css
ftw/news/browser/resources/news.scss
ftw/news/browser/templates/mopage_news.pt
ftw/news/browser/templates/news_listing.pt
ftw/news/browser/templates/news_listing_block.pt
ftw/news/browser/templates/news_listing_rss.pt
ftw/news/contents/__init__.py
ftw/news/contents/common.py
ftw/news/contents/news.py
ftw/news/contents/news_folder.py
ftw/news/contents/news_listing_block.py
ftw/news/locales/ftw.news-manual.pot
ftw/news/locales/ftw.news.pot
ftw/news/locales/plone.pot
ftw/news/locales/de/LC_MESSAGES/ftw.news.po
ftw/news/locales/de/LC_MESSAGES/plone.po
ftw/news/portlets/__init__.py
ftw/news/portlets/configure.zcml
ftw/news/portlets/news_archive_portlet.py
ftw/news/portlets/news_portlet.py
ftw/news/portlets/templates/news_archive_portlet.pt
ftw/news/portlets/templates/news_portlet.pt
ftw/news/profiles/default/browserlayer.xml
ftw/news/profiles/default/cssregistry.xml
ftw/news/profiles/default/jsregistry.xml
